moveread/finetuning/__init__.py
moveread/finetuning/__init__.pyi
moveread/finetuning/cli.py
moveread/finetuning/data.py
moveread/finetuning/hparams.py
moveread/finetuning/loop.py
moveread/finetuning/main.py
moveread/finetuning/model.py
moveread/finetuning/steps.py
moveread_finetuning-0.1.5.dist-info/METADATA
moveread_finetuning-0.1.5.dist-info/WHEEL
moveread_finetuning-0.1.5.dist-info/entry_points.txt
moveread_finetuning-0.1.5.dist-info/top_level.txt
moveread_finetuning-0.1.5.dist-info/RECORD
